path.py
setup.py
lilydjwg.Path.egg-info/PKG-INFO
lilydjwg.Path.egg-info/SOURCES.txt
lilydjwg.Path.egg-info/dependency_links.txt
lilydjwg.Path.egg-info/not-zip-safe
lilydjwg.Path.egg-info/top_level.txt