Metadata-Version: 1.0
Name: lilydjwg.Path
Version: 0.2
Summary: An object that handles path more easily
Home-page: http://github.com/lilydjwg/winterpy
Author: lilydjwg
Author-email: lilydjwg@gmail.com
License: GPL
Platform: UNKNOWN
